MANIFEST.in
README.md
requirements.txt
setup.py
redlink/__init__.py
redlink/analysis.py
redlink/client.py
redlink/data.py
redlink/format.py
redlink.egg-info/PKG-INFO
redlink.egg-info/SOURCES.txt
redlink.egg-info/dependency_links.txt
redlink.egg-info/requires.txt
redlink.egg-info/top_level.txt
tests/__init__.py
tests/test-analysis.py
tests/test-clients.py
tests/test-data.py
tests/test-format.py
tests/utils.py