Metadata-Version: 1.1
Name: redlink
Version: 1.0.1
Summary: Redlink Python SDK
Home-page: https://github.com/redlink-gmbh/redlink-python-sdk
Author: Sergio Fernandez
Author-email: sergio.fernandez@redlink.co
License: Apache Software License 2.0
Download-URL: https://github.com/redlink-gmbh/redlink-python-sdk/releases
Keywords: python redlink api client sdk linkeddata rdf marmotta analysis nlp stanbol
Platform: any
Classifier: Development Status :: 4 - Beta
Classifier: Intended Audience :: Developers
Classifier: License :: OSI Approved :: Apache Software License
Classifier: Operating System :: OS Independent
Classifier: Programming Language :: Python :: 2
Classifier: Programming Language :: Python :: 3
Requires: requests
Requires: rdflib
Requires: SPARQLWrapper
